fiatlight/.gitignore
fiatlight/__init__.py
fiatlight/py.typed
fiatlight/assets/images/bear_transparent.png
fiatlight/assets/images/house.jpg
fiatlight/assets/images/tennis.jpg
fiatlight/assets/logo/logo_fiatlight.jpg
fiatlight/assets/logo/logo_photo.jpg
fiatlight/demos/__init__.py
fiatlight/demos/ai_image_gen/__init__.py
fiatlight/demos/ai_image_gen/demo_meme_generator.py
fiatlight/demos/ai_image_gen/demo_sdxl_toon_edges.py
fiatlight/demos/ai_image_gen/fiat_settings/Meme_Generator.fiat_user.json
fiatlight/demos/ai_image_gen/fiat_settings/Meme_Generator.ini
fiatlight/demos/ai_image_gen/fiat_settings/Meme_Generator.node_editor.json
fiatlight/demos/ai_tuning/grokking.ipynb
fiatlight/demos/ai_tuning/grokking_tune.py
fiatlight/demos/ai_tuning/iris_train_full_app.py
fiatlight/demos/ai_tuning/iris_train_tuning.py
fiatlight/demos/ai_tuning/fiat_settings/grokking_tune.fiat_user.json
fiatlight/demos/ai_tuning/fiat_settings/grokking_tune.ini
fiatlight/demos/ai_tuning/fiat_settings/grokking_tune.node_editor.json
fiatlight/demos/ai_tuning/fiat_settings/iris.fiat_user.json
fiatlight/demos/ai_tuning/fiat_settings/iris.ini
fiatlight/demos/ai_tuning/fiat_settings/iris.node_editor.json
fiatlight/demos/ai_tuning/fiat_settings/iris_train_full_app.fiat_user.json
fiatlight/demos/ai_tuning/fiat_settings/iris_train_full_app.ini
fiatlight/demos/ai_tuning/fiat_settings/iris_train_full_app.node_editor.json
fiatlight/demos/ai_tuning/fiat_settings/iris_train_tuning.fiat_user.json
fiatlight/demos/ai_tuning/fiat_settings/iris_train_tuning.ini
fiatlight/demos/ai_tuning/fiat_settings/iris_with_global_state.fiat_user.json
fiatlight/demos/ai_tuning/fiat_settings/iris_with_global_state.ini
fiatlight/demos/ai_tuning/fiat_settings/iris_with_global_state.node_editor.json
fiatlight/demos/custom_graph/__init__.py
fiatlight/demos/custom_graph/demo_custom_graph.py
fiatlight/demos/custom_graph/fiat_settings/demo_custom_graph.fiat_graph.json
fiatlight-0.5.0.dist-info/METADATA
fiatlight-0.5.0.dist-info/WHEEL
fiatlight-0.5.0.dist-info/entry_points.txt
fiatlight-0.5.0.dist-info/licenses/LICENSE
fiatlight-0.5.0.dist-info/RECORD
