Metadata-Version: 2.4
Name: fiatlight
Version: 0.5.0
Summary: fiatlight: shine light inside your algorithm pipelines
Project-URL: homepage, https://pthom.github.io/fiatlight/
Project-URL: repository, https://github.com/pthom/fiatlight/
Project-URL: documentation, https://pthom.github.io/fiatlight/
Author-email: Pascal Thomet <pthomet@gmail.com>
License-File: LICENSE
Keywords: python
Classifier: Development Status :: 4 - Beta
Classifier: Environment :: Console
Classifier: Intended Audience :: Developers
Classifier: Programming Language :: Python
Classifier: Topic :: Software Development :: Libraries :: Python Modules
Classifier: Typing :: Typed
Requires-Python: >=3.10
Requires-Dist: imgui-bundle>=1.92.4
Requires-Dist: matplotlib
Requires-Dist: numpy
Requires-Dist: opencv-python
Requires-Dist: pandas
Requires-Dist: pillow
Requires-Dist: pydantic
Requires-Dist: tabulate
Requires-Dist: types-pillow
